fulladder_raw/fulladder.sv
module fulladder (
    input  logic a,    // First input
    input  logic b,    // Second input
    input  logic cin,  // Carry in
    output logic sum,  // Sum output
    output logic cout  // Carry out
);

    // Full adder logic
    assign sum = a ^ b ^ cin;
    assign cout = (a & b) | (cin & (a ^ b));

    // Dump waves
    initial begin
        $dumpfile("fulladder.vcd");
        $dumpvars(0, fulladder);
    end

endmodule

fulladder_raw/fulladder.vcd
$date
	Thu Apr  3 16:54:34 2025
$end
$version
	Icarus Verilog
$end
$timescale
	1ps
$end
$scope module fulladder $end
$var wire 1 ! a $end
$var wire 1 " b $end
$var wire 1 # cin $end
$var wire 1 $ cout $end
$var wire 1 % sum $end
$upscope $end
$enddefinitions $end
$comment Show the parameter values. $end
$dumpall
$end
#0
$dumpvars
0%
0$
0#
0"
0!
$end
#1000
1%
1#
#2000
0#
1"
#3000
1$
0%
1#
#4000
0$
1%
0#
0"
1!
#5000
1$
0%
1#
#6000
0#
1"
#7000
1%
1#
